aspire_gw/__init__.py
aspire_gw/flows.py
aspire_gw/gw_aspire.py
aspire_gw-0.1.0a2.dist-info/licenses/LICENSE.md
aspire_gw-0.1.0a2.dist-info/METADATA
aspire_gw-0.1.0a2.dist-info/WHEEL
aspire_gw-0.1.0a2.dist-info/entry_points.txt
aspire_gw-0.1.0a2.dist-info/top_level.txt
aspire_gw-0.1.0a2.dist-info/RECORD
