Metadata-Version: 2.4
Name: aspire-gw
Version: 0.1.0a2
Summary: Gravitational-wave extensions to aspire
Author-email: "Michael J. Williams" <michaeljw1@googlemail.com>
License: MIT
Classifier: Programming Language :: Python :: 3
Requires-Python: >=3.10
License-File: LICENSE.md
Requires-Dist: aspire-inference
Provides-Extra: jax
Requires-Dist: jax; extra == "jax"
Requires-Dist: jaxlib; extra == "jax"
Requires-Dist: flowjax; extra == "jax"
Provides-Extra: gwflow
Requires-Dist: gwflow; extra == "gwflow"
Requires-Dist: zuko; extra == "gwflow"
Requires-Dist: matplotlib; extra == "gwflow"
Requires-Dist: aspire-inference[torch]; extra == "gwflow"
Provides-Extra: bilby
Requires-Dist: aspire-bilby; extra == "bilby"
Requires-Dist: bilby>=2.3.0; extra == "bilby"
Provides-Extra: test
Requires-Dist: pytest; extra == "test"
Dynamic: license-file
